meerkat/sites.py
meerkat/exceptions.py
meerkat/apps.py
meerkat/views.py
meerkat/__init__.py
meerkat/models.py
meerkat/admin.py
meerkat/utils/ip_info.py
meerkat/utils/url.py
meerkat/utils/time.py
meerkat/utils/geolocation.py
meerkat/utils/list.py
meerkat/utils/thread.py
meerkat/utils/file.py
meerkat/utils/__init__.py
meerkat/logs/parsers.py
meerkat/logs/charts.py
meerkat/logs/boxes.py
meerkat/logs/data.py
meerkat/logs/stats.py
meerkat/logs/views.py
meerkat/logs/urls.py
meerkat/logs/__init__.py
meerkat/logs/models.py
meerkat/logs/admin.py
meerkat/marchan/boxes.py
meerkat/marchan/checks.py
meerkat/marchan/views.py
meerkat/marchan/urls.py
meerkat/marchan/__init__.py
meerkat/migrations/0001_initial.py
meerkat/migrations/0002_auto_20170515_1230.py
meerkat/migrations/__init__.py
meerkat/templates/meerkat/main.html
meerkat/templates/meerkat/logs/links.html
meerkat/templates/meerkat/logs/status_codes_by_date.html
meerkat/templates/meerkat/widgets/highcharts.html
meerkat/templates/meerkat/widgets/table.html
meerkat/templates/meerkat/archan/evaluation.html
meerkat/templates/meerkat/archan/links.html
meerkat/static/meerkat/highcharts/highcharts.src.js
meerkat/static/meerkat/highcharts/highcharts-3d.js
meerkat/static/meerkat/highcharts/.gitignore
meerkat/static/meerkat/highcharts/highcharts-3d.js.map
meerkat/static/meerkat/highcharts/highcharts.js.map
meerkat/static/meerkat/highcharts/highmaps.js
meerkat/static/meerkat/highcharts/bower.json
meerkat/static/meerkat/highcharts/highcharts.js
meerkat/static/meerkat/highcharts/highstock.js.map
meerkat/static/meerkat/highcharts/highcharts-more.js.map
meerkat/static/meerkat/highcharts/package.json
meerkat/static/meerkat/highcharts/.bower.json
meerkat/static/meerkat/highcharts/highcharts-3d.src.js
meerkat/static/meerkat/highcharts/README.md
meerkat/static/meerkat/highcharts/highmaps.src.js
meerkat/static/meerkat/highcharts/highstock.src.js
django_meerkat-0.2.6.dist-info/metadata.json
django_meerkat-0.2.6.dist-info/DESCRIPTION.rst
django_meerkat-0.2.6.dist-info/top_level.txt
django_meerkat-0.2.6.dist-info/WHEEL
django_meerkat-0.2.6.dist-info/RECORD
django_meerkat-0.2.6.dist-info/METADATA
