Metadata-Version: 2.0
Name: django-meerkat
Version: 0.2.6
Summary: Security audit tool for Django sites
Home-page: https://github.com/Genida/django-meerkat
Author: Timothee Mazzucotelli
Author-email: timothee.mazzucotelli@gmail.com
License: ISC
Keywords: security,audit,admin,dashboard,logs,analysis,django
Platform: UNKNOWN
Classifier: Development Status :: 3 - Alpha
Classifier: Intended Audience :: Developers
Classifier: Intended Audience :: Science/Research
Classifier: License :: OSI Approved :: ISC License (ISCL)
Classifier: Operating System :: Unix
Classifier: Framework :: Django
Classifier: Programming Language :: Python
Classifier: Programming Language :: Python :: 2.7
Classifier: Programming Language :: Python :: 3
Classifier: Programming Language :: Python :: 3.4
Classifier: Programming Language :: Python :: 3.5
Classifier: Programming Language :: Python :: 3.6
Classifier: Programming Language :: Python :: Implementation :: PyPy
Classifier: Topic :: Utilities
Requires-Dist: django-suit-dashboard
Requires-Dist: python-dateutil
Requires-Dist: requests
Requires-Dist: django-app-settings
Requires-Dist: archan
Requires-Dist: dependenpy
